{"name":"布基纳法索","code":"BFA","states":[{"citys":[{"name":"巴雷","code":"BAL"},{"name":"巴姆","code":"BAM"},{"name":"巴瓦","code":"BAN"},{"name":"巴泽加","code":"BAZ"},{"name":"波尼","code":"PON"},{"name":"布尔古","code":"BLG"},{"name":"布尔基恩德","code":"BOK"},{"name":"布古里巴","code":"BOR"},{"name":"冈祖尔古","code":"GAN"},{"name":"古尔马","code":"GOU"},{"name":"济罗","code":"ZIR"},{"name":"卡焦戈","code":"KAD"},{"name":"凯内杜古","code":"KEN"},{"name":"科蒙加里","code":"KOO"},{"name":"科莫埃","code":"COM"},{"name":"孔皮恩加","code":"KOP"},{"name":"孔西","code":"KOS"},{"name":"库尔佩罗戈","code":"KOL"},{"name":"库尔维奥戈","code":"KOW"},{"name":"库里滕加","code":"KOT"},{"name":"雷拉巴","code":"LER"},{"name":"罗卢姆","code":"LOR"},{"name":"穆翁","code":"MOU"},{"name":"纳门滕加","code":"NAM"},{"name":"纳乌里","code":"NAH"},{"name":"纳亚拉","code":"NAY"},{"name":"尼亚尼亚","code":"GNA"},{"name":"努姆比埃尔","code":"NOU"},{"name":"帕索雷","code":"PAS"},{"name":"塞诺","code":"SEN"},{"name":"桑吉","code":"SAG"},{"name":"桑马滕加","code":"SAM"},{"name":"苏鲁","code":"SOR"},{"name":"苏姆","code":"SOM"},{"name":"塔波阿","code":"TAP"},{"name":"图伊","code":"TUY"},{"name":"乌埃","code":"HOU"},{"name":"乌布里滕加","code":"OUB"},{"name":"乌达兰","code":"OUD"},{"name":"锡西里","code":"SIS"},{"name":"亚加","code":"YAG"},{"name":"亚滕加","code":"YAT"},{"name":"伊奥巴","code":"IOA"},{"name":"宗德韦奥戈","code":"ZOW"},{"name":"宗多马","code":"ZOD"}]}]}