{"name":"日本","code":"JPN","states":[{"citys":[{"name":"爱媛","code":"38"},{"name":"爱知","code":"23"},{"name":"北海道","code":"1"},{"name":"兵库","code":"28"},{"name":"冲绳","code":"47"},{"name":"茨城","code":"8"},{"name":"大阪","code":"27"},{"name":"大分","code":"44"},{"name":"岛根","code":"32"},{"name":"徳岛","code":"36"},{"name":"东京","code":"13"},{"name":"福岛","code":"7"},{"name":"福冈","code":"40"},{"name":"福井","code":"18"},{"name":"富山","code":"16"},{"name":"冈山","code":"33"},{"name":"高知","code":"39"},{"name":"宮城","code":"4"},{"name":"宫崎","code":"45"},{"name":"广岛","code":"34"},{"name":"和歌山","code":"30"},{"name":"京都","code":"26"},{"name":"静冈","code":"22"},{"name":"枥木","code":"9"},{"name":"鹿儿岛","code":"46"},{"name":"奈良","code":"29"},{"name":"鸟取","code":"31"},{"name":"岐阜","code":"21"},{"name":"埼玉","code":"11"},{"name":"千叶","code":"12"},{"name":"青森","code":"2"},{"name":"秋田","code":"5"},{"name":"群马","code":"10"},{"name":"三重","code":"24"},{"name":"山口","code":"35"},{"name":"山梨","code":"19"},{"name":"山形","code":"6"},{"name":"神奈川","code":"14"},{"name":"石川","code":"17"},{"name":"香川","code":"37"},{"name":"新潟","code":"15"},{"name":"熊本","code":"43"},{"name":"岩手","code":"3"},{"name":"长崎","code":"42"},{"name":"长野","code":"20"},{"name":"滋贺","code":"25"},{"name":"佐贺","code":"41"}]}]}